odoo/addons/maintenance_request_tags/README.rst
odoo/addons/maintenance_request_tags/__init__.py
odoo/addons/maintenance_request_tags/__manifest__.py
odoo/addons/maintenance_request_tags/i18n/es.po
odoo/addons/maintenance_request_tags/i18n/it.po
odoo/addons/maintenance_request_tags/i18n/maintenance_request_tags.pot
odoo/addons/maintenance_request_tags/models/__init__.py
odoo/addons/maintenance_request_tags/models/maintenance_request.py
odoo/addons/maintenance_request_tags/models/maintenance_request_tag.py
odoo/addons/maintenance_request_tags/readme/CONTRIBUTORS.md
odoo/addons/maintenance_request_tags/readme/DESCRIPTIONS.md
odoo/addons/maintenance_request_tags/security/ir.model.access.csv
odoo/addons/maintenance_request_tags/static/description/icon.png
odoo/addons/maintenance_request_tags/views/maintenance_request.xml
odoo/addons/maintenance_request_tags/views/maintenance_request_tag.xml
odoo_addon_maintenance_request_tags-18.0.1.0.0.3.dist-info/METADATA
odoo_addon_maintenance_request_tags-18.0.1.0.0.3.dist-info/WHEEL
odoo_addon_maintenance_request_tags-18.0.1.0.0.3.dist-info/top_level.txt
odoo_addon_maintenance_request_tags-18.0.1.0.0.3.dist-info/RECORD
